muck_out/__init__.py
muck_out/__main__.py
muck_out/exceptions.py
muck_out/py.typed
muck_out/test_actor_update.py
muck_out/test_all.py
muck_out/test_init.py
muck_out/test_main.py
muck_out/test_object.py
muck_out/version.py
muck_out/cattle_grid/__init__.py
muck_out/cattle_grid/fetch.py
muck_out/cattle_grid/methods.py
muck_out/cattle_grid/test_fetch.py
muck_out/cattle_grid/test_injection.py
muck_out/cattle_grid/transform.py
muck_out/derived/__init__.py
muck_out/derived/actor_header_info.py
muck_out/derived/object_meta_info.py
muck_out/derived/test_actor_header_info.py
muck_out/derived/test_object_meta_information.py
muck_out/derived/test_util.py
muck_out/derived/util.py
muck_out/extension/__init__.py
muck_out/extension/config.py
muck_out/extension/test_extension.py
muck_out/process/__init__.py
muck_out/process/activity.py
muck_out/process/actor.py
muck_out/process/base.py
muck_out/process/collection.py
muck_out/process/object.py
muck_out/process/test_activity.py
muck_out/process/test_actor.py
muck_out/process/test_collection.py
muck_out/process/test_collection_stub.py
muck_out/process/test_object.py
muck_out/process/test_object_fep_e232.py
muck_out/pydantic_types/__init__.py
muck_out/pydantic_types/list_utils.py
muck_out/pydantic_types/methods.py
muck_out/schemas/__init__.py
muck_out/schemas/clean.py
muck_out/schemas/test_clean.py
muck_out/sub_types/__init__.py
muck_out/sub_types/attachment.py
muck_out/sub_types/tag.py
muck_out/sub_types/test_tag.py
muck_out/sub_types/test_test_actor_attachment.py
muck_out/testing/__init__.py
muck_out/testing/examples.py
muck_out/transform/__init__.py
muck_out/transform/attachment.py
muck_out/transform/list_utils.py
muck_out/transform/test_attachment.py
muck_out/transform/test_utils.py
muck_out/transform/utils.py
muck_out/types/__init__.py
muck_out/types/common/__init__.py
muck_out/types/common/actor.py
muck_out/types/common/object.py
muck_out/types/stubs/__init__.py
muck_out/types/stubs/activity.py
muck_out/types/stubs/actor.py
muck_out-0.3.15.dist-info/METADATA
muck_out-0.3.15.dist-info/WHEEL
muck_out-0.3.15.dist-info/RECORD
