Metadata-Version: 2.4
Name: muck-out
Version: 0.3.15
Summary: Add your description here
Requires-Python: >=3.11
Requires-Dist: bovine>=0.5.14
Requires-Dist: nh3>=0.2.20
Requires-Dist: pydantic>=2.10.4
Requires-Dist: uuid6>=2024.7.10
Provides-Extra: cattle-grid
Requires-Dist: cattle-grid>=0.5.11; extra == 'cattle-grid'
Provides-Extra: markdown
Requires-Dist: markdown>=3.9; extra == 'markdown'
